README.md
setup.cfg
setup.py
JscorpPayments/__init__.py
JscorpPayments/admin.py
JscorpPayments/apps.py
JscorpPayments/authentication.py
JscorpPayments/methods_subscribe_api.py
JscorpPayments/models.py
JscorpPayments/status.py
JscorpPayments/views.py
JscorpPayments.egg-info/PKG-INFO
JscorpPayments.egg-info/SOURCES.txt
JscorpPayments.egg-info/dependency_links.txt
JscorpPayments.egg-info/requires.txt
JscorpPayments.egg-info/top_level.txt
JscorpPayments/management/__init__.py
JscorpPayments/management/commands/__init__.py
JscorpPayments/management/commands/create_paycom_user.py
JscorpPayments/migrations/0001_initial.py
JscorpPayments/migrations/0002_auto_20200111_1714.py
JscorpPayments/migrations/0003_auto_20210303_2348.py
JscorpPayments/migrations/0004_auto_20210304_0101.py
JscorpPayments/migrations/__init__.py
JscorpPayments/serializers/__init__.py
JscorpPayments/serializers/payme_operation.py